timelapser/__init__.py
timelapser/__main__.py
timelapser/main.py
timelapser/recorder.py
timelapser/utils.py
timelapser-0.1.3.dist-info/LICENSE
timelapser-0.1.3.dist-info/METADATA
timelapser-0.1.3.dist-info/WHEEL
timelapser-0.1.3.dist-info/entry_points.txt
timelapser-0.1.3.dist-info/top_level.txt
timelapser-0.1.3.dist-info/RECORD
