Metadata-Version: 2.1
Name: timelapser
Version: 0.1.3
Summary: Record and save time-lapse videos while you work.
Home-page: https://github.com/asibhossen897/TimeLapser
Author: Asib Hossen
Author-email: dev.asib@proton.me
Classifier: Programming Language :: Python :: 3
Classifier: License :: OSI Approved :: MIT License
Classifier: Operating System :: OS Independent
Requires-Python: >=3.10
License-File: LICENSE
Requires-Dist: typer
Requires-Dist: numpy
Requires-Dist: opencv-python-headless
Requires-Dist: mss
Requires-Dist: pynput
Requires-Dist: rich
